IF4.py
jsonGen2.py
Examples/basic_example.py
Examples/using_decorators.py
Examples/generating_files/main.py
Examples/loading_data/main.py
decorators/defaultIF4.py
decorators/immutableIF4.py
decorators/manuvalIF4.py
decorators/multipleIF4.py
decorators/optionalIF4.py
decorators/restrictedIF4.py
Interface2_py_ashersopro2-0.0.1.dist-info/LICENSE
Interface2_py_ashersopro2-0.0.1.dist-info/METADATA
Interface2_py_ashersopro2-0.0.1.dist-info/WHEEL
Interface2_py_ashersopro2-0.0.1.dist-info/top_level.txt
Interface2_py_ashersopro2-0.0.1.dist-info/RECORD
