Metadata-Version: 2.1
Name: Interface2-py-ashersopro2
Version: 0.0.1
Summary: A python implementation of typescript interfaces
Author: Asher
Classifier: Programming Language :: Python :: 3
Classifier: License :: OSI Approved :: MIT License
Classifier: Operating System :: OS Independent
Requires-Python: >=3.9
License-File: LICENSE
Requires-Dist: requests
Requires-Dist: typing
Requires-Dist: functools
Requires-Dist: json
Requires-Dist: builtins
Requires-Dist: importlib-metadata ; python_version == "3.10"
